ansi256/__init__.py
ansi256/ansi256.py
ansi256colors-1.0.0.dist-info/LICENSE
ansi256colors-1.0.0.dist-info/METADATA
ansi256colors-1.0.0.dist-info/WHEEL
ansi256colors-1.0.0.dist-info/entry_points.txt
ansi256colors-1.0.0.dist-info/top_level.txt
ansi256colors-1.0.0.dist-info/RECORD
