Metadata-Version: 2.1
Name: ansi256colors
Version: 1.0.0
Summary: A tool to print and demo ansi color codes for a 256 color terminal
Author: Michael Cox
License: GNU GENERAL PUBLIC LICENSE
Project-URL: Homepage, https://github.com/michael-cox/ansi256-colors
Keywords: ansi,ansi256,color,codes,color codes,console,terminal,emulator,color,256
Classifier: Development Status :: 4 - Beta
Classifier: Intended Audience :: Developers
Classifier: Topic :: System :: Console Fonts
Classifier: License :: OSI Approved :: GNU General Public License v3 (GPLv3)
Classifier: Programming Language :: Python :: 3
Classifier: Programming Language :: Python :: 3.7
Classifier: Programming Language :: Python :: 3.8
Classifier: Programming Language :: Python :: 3.9
Classifier: Programming Language :: Python :: 3.10
Classifier: Programming Language :: Python :: 3 :: Only
Requires-Python: <4,>=3.7
License-File: LICENSE
Requires-Dist: tabulate
